ig_degree_betweenness/__init__.py
ig_degree_betweenness/__main__.py
ig_degree_betweenness/core.py
ig_degree_betweenness-0.1.4.dist-info/METADATA
ig_degree_betweenness-0.1.4.dist-info/WHEEL
ig_degree_betweenness-0.1.4.dist-info/entry_points.txt
ig_degree_betweenness-0.1.4.dist-info/top_level.txt
ig_degree_betweenness-0.1.4.dist-info/RECORD
