Metadata-Version: 2.4
Name: ig_degree_betweenness
Version: 0.1.4
Summary: Smith-Pittman Community Detection Algorithm for 'igraph' Objects (2024)
Author-email: Benjamin Smith <benyamin.smith@mail.utoronto.ca>, Tyler Pittman <Tyler.Pittman@uhn.ca>, Wei Xu <Wei.Xu@uhn.ca>
License: MIT
Project-URL: Homepage, https://github.com/benyamindsmith/ig_degree_betweenness_py
Project-URL: Benjamin Smith ORCID, https://orcid.org/0009-0007-2206-0177
Project-URL: Tyler Pittman ORCID, https://orcid.org/0000-0002-5013-6980
Project-URL: Wei Xu ORCID, https://orcid.org/0000-0002-0257-8856
Keywords: igraph
Classifier: Operating System :: OS Independent
Classifier: Programming Language :: Python :: 3
Classifier: License :: OSI Approved :: MIT License
Classifier: Intended Audience :: Science/Research
Classifier: Topic :: Scientific/Engineering :: Information Analysis
Classifier: Topic :: Scientific/Engineering :: Artificial Intelligence
Classifier: Topic :: Software Development :: Libraries :: Python Modules
Requires-Python: >=3.7
Requires-Dist: python-igraph
